mdd/__init__.py
mdd/mdd.py
mdd/nx.py
mdd-0.3.7.dist-info/LICENSE
mdd-0.3.7.dist-info/WHEEL
mdd-0.3.7.dist-info/METADATA
mdd-0.3.7.dist-info/RECORD
